{"version":1,"resource":"file:///home/spartan/.config/eww/modules/quick_settings.yuck","entries":[{"id":"gkia.yuck","timestamp":1700794171074},{"id":"AJlh.yuck","source":"undoRedo.source","timestamp":1700794187845},{"id":"RigS.yuck","timestamp":1700794536093},{"id":"36cZ.yuck","timestamp":1700794564172},{"id":"tF6X.yuck","timestamp":1700795409667},{"id":"NAtd.yuck","timestamp":1700795495559},{"id":"8YcU.yuck","timestamp":1700795508694},{"id":"badA.yuck","timestamp":1700795684943},{"id":"gekG.yuck","timestamp":1700795757527},{"id":"tx6z.yuck","source":"undoRedo.source","timestamp":1700795855915},{"id":"JNlP.yuck","timestamp":1700796103659},{"id":"dEzW.yuck","timestamp":1700796114553}]}